2gis-1.3.1.dist-info/DESCRIPTION.rst
2gis-1.3.1.dist-info/METADATA
2gis-1.3.1.dist-info/RECORD
2gis-1.3.1.dist-info/WHEEL
2gis-1.3.1.dist-info/metadata.json
2gis-1.3.1.dist-info/top_level.txt
dgis/__init__.py
dgis/binder.py
dgis/exceptions.py
dgis/utils.py
tests/__init__.py
tests/main.py
tests/project_list.py
tests/rubricator.py
